automod/__init__.py
automod/automod.py
automod/csview.py
automod/curvescene.py
automod/curveview.py
automod/gridline.py
automod/gridpoint.py
automod/helixpoint.py
automod/icons.py
automod/icons.qrc
automod/mainwindow.py
automod/nodepoint.py
automod/pathcurve.py
automod/pathline.py
automod/storage3d.py
automod/icons/app_icon.png
automod/icons/arrow_black.png
automod/icons/arrow_blue.png
automod/icons/arrow_green.png
automod/icons/arrow_red.png
automod/icons/connect.png
automod/icons/disconnect_next.png
automod/icons/disconnect_prev.png
automod/icons/honeycomb.png
automod/icons/import.png
automod/icons/insert_plus.png
automod/icons/interpolate.png
automod/icons/json.png
automod/icons/print.png
automod/icons/renum.png
automod/icons/restore.png
automod/icons/rotate_black.png
automod/icons/rotate_blue.png
automod/icons/rotate_green.png
automod/icons/rotate_red.png
automod/icons/save.png
automod/icons/square.png
automod/icons/trash.png
automod/icons/zoom.png
automod-0.0.5.dist-info/METADATA
automod-0.0.5.dist-info/WHEEL
automod-0.0.5.dist-info/entry_points.txt
automod-0.0.5.dist-info/licenses/LICENSE.txt
automod-0.0.5.dist-info/RECORD
