Metadata-Version: 2.4
Name: automod
Version: 0.0.5
Summary: Automated modification and crossover placement for the design of curved DNA origami structures.
Project-URL: Homepage, https://github.com/AutoMod-DNA/automod
Project-URL: Issues, https://github.com/AutoMod-DNA/automod/issues
Author-email: Elina Heikkilä <elina.s.heikkila@aalto.fi>
License-Expression: MIT
License-File: LICENSE.txt
Classifier: Development Status :: 4 - Beta
Classifier: Intended Audience :: Science/Research
Classifier: Operating System :: OS Independent
Classifier: Programming Language :: Python :: 3
Requires-Python: >=3.9
Requires-Dist: numpy>=2.0.0
Requires-Dist: pyside6
Requires-Dist: scipy>=1.15.3
